AUTHORS
ChangeLog
LICENSE
README.md
example.py
kale.jpg
publish.sh
requirements.txt
setup.cfg
setup.py
test-requirements.txt
data_kale/configuration.py
data_kale/download.py
data_kale/list_remote.py
data_kale/path.py
data_kale/remote_resource.py
data_kale/upload.py
data_kale/utils.py
data_kale.egg-info/PKG-INFO
data_kale.egg-info/SOURCES.txt
data_kale.egg-info/dependency_links.txt
data_kale.egg-info/entry_points.txt
data_kale.egg-info/not-zip-safe
data_kale.egg-info/pbr.json
data_kale.egg-info/requires.txt
data_kale.egg-info/top_level.txt
data_kale/object_/identical.py
data_kale/object_/local_object.py
data_kale/object_/object_.py
data_kale/object_/remote_object.py
tests/conftest.py
tests/test_download.py
tests/test_list_remote.py
tests/test_upload.py
tests/fixture/test_get_object.py
tests/fixture/test_get_path.py
tests/fixture/test_repository.py
tests/fixture/test_repository_name.py
tests/fixture/test_repository_path.py
tests/fixture/test_root.py