Metadata-Version: 1.2
Name: data-kale
Version: 0.1.3
Summary: Simple Data Lake to sync data repositories to S3 compatible buckets.
Home-page: UNKNOWN
Author: "Jim Holmstr\u00F6m"
Author-email: jim@aiwizo.com
License: UNKNOWN
Project-URL: Source Code, https://github.com/aiwizo/data-kale/
Keywords: data,lake,repository
Platform: UNKNOWN
